monetdblite/exceptions.py
monetdblite/cursors.py
monetdblite/connections.py
monetdblite/__init__.py
monetdblite/monetize.py
monetdblite/libmonetdb5.cpython-37m-x86_64-linux-gnu.so
monetdblite/embeddedmonetdb.py
monetdblite-0.6.4.dist-info/LICENSE.txt
monetdblite-0.6.4.dist-info/top_level.txt
monetdblite-0.6.4.dist-info/RECORD
monetdblite-0.6.4.dist-info/METADATA
monetdblite-0.6.4.dist-info/WHEEL
